acenus/__init__.py
acenus/executors_pool.py
acenus/usecase.py
acenus-0.2.2.dist-info/LICENSE
acenus-0.2.2.dist-info/WHEEL
acenus-0.2.2.dist-info/METADATA
acenus-0.2.2.dist-info/RECORD
