Metadata-Version: 2.1
Name: acenus
Version: 0.2.2
Summary: 
Author: tsarbas
Requires-Python: >=3.9,<4.0
Classifier: Programming Language :: Python :: 3
Classifier: Programming Language :: Python :: 3.10
Classifier: Programming Language :: Python :: 3.9
Requires-Dist: loguru (>=0.5.3,<0.6.0)
